<?xml version="1.0" encoding="utf-8"?>
<root>
	<monster>
		<monsterId>1</monsterId>
		<monsterName>黑野猪</monsterName>
		<speed>12</speed>
		<attackPower>5</attackPower>
		<defensivePower>2</defensivePower>
		<bloodTotalVolume>20</bloodTotalVolume>
		<magicTotalVolume>20</magicTotalVolume>
		<attackLength>5</attackLength>
		<rank>1</rank>
		
		<srcInfo>
			<srcName>monster/blackpig.png</srcName>
			<rowFramCount>4</rowFramCount>
			<colFramCount>9</colFramCount>
		</srcInfo>
		<leftFrames>
			<frame>
				<row>1</row>
				<col>0</col>
			</frame>
			<frame>
				<row>1</row>
				<col>1</col>
			</frame>
			<frame>
				<row>1</row>
				<col>2</col>
			</frame>
			<frame>
				<row>1</row>
				<col>3</col>
			</frame>
		</leftFrames>
		<rightFrames>
			<frame>
				<row>2</row>
				<col>0</col>
			</frame>
			<frame>
				<row>2</row>
				<col>1</col>
			</frame>
			<frame>
				<row>2</row>
				<col>2</col>
			</frame>
			<frame>
				<row>2</row>
				<col>3</col>
			</frame>
		</rightFrames>
	</monster>
	<monster>
		<monsterId>2</monsterId>
		<monsterName>企鹅</monsterName>
		<speed>10</speed>
		<attackPower>8</attackPower>
		<defensivePower>3</defensivePower>
		<bloodTotalVolume>30</bloodTotalVolume>
		<magicTotalVolume>30</magicTotalVolume>
		<attackLength>5</attackLength>
		<rank>2</rank>
		<srcInfo>
			<srcName>monster/qq.png</srcName>
			<rowFramCount>4</rowFramCount>
			<colFramCount>9</colFramCount>
		</srcInfo>
		<leftFrames>
			<frame>
				<row>1</row>
				<col>0</col>
			</frame>
			<frame>
				<row>1</row>
				<col>1</col>
			</frame>
			<frame>
				<row>1</row>
				<col>2</col>
			</frame>
			<frame>
				<row>1</row>
				<col>3</col>
			</frame>
		</leftFrames>
		<rightFrames>
			<frame>
				<row>2</row>
				<col>0</col>
			</frame>
			<frame>
				<row>2</row>
				<col>1</col>
			</frame>
			<frame>
				<row>2</row>
				<col>2</col>
			</frame>
			<frame>
				<row>2</row>
				<col>3</col>
			</frame>
		</rightFrames>
	</monster>
	<monster>
		<monsterId>3</monsterId>
		<monsterName>白眼独怪</monsterName>
		<speed>10</speed>
		<attackPower>8</attackPower>
		<defensivePower>3</defensivePower>
		<bloodTotalVolume>30</bloodTotalVolume>
		<magicTotalVolume>30</magicTotalVolume>
		<attackLength>5</attackLength>
		<rank>2</rank>
		<srcInfo>
			<srcName>monster/baiyanduguai.png</srcName>
			<rowFramCount>4</rowFramCount>
			<colFramCount>9</colFramCount>
		</srcInfo>
		<leftFrames>
			<frame>
				<row>1</row>
				<col>0</col>
			</frame>
			<frame>
				<row>1</row>
				<col>1</col>
			</frame>
			<frame>
				<row>1</row>
				<col>2</col>
			</frame>
			<frame>
				<row>1</row>
				<col>3</col>
			</frame>
		</leftFrames>
		<rightFrames>
			<frame>
				<row>2</row>
				<col>0</col>
			</frame>
			<frame>
				<row>2</row>
				<col>1</col>
			</frame>
			<frame>
				<row>2</row>
				<col>2</col>
			</frame>
			<frame>
				<row>2</row>
				<col>3</col>
			</frame>
		</rightFrames>
	</monster>
	<monster>
		<monsterId>4</monsterId>
		<monsterName>包厢王</monsterName>
		<speed>10</speed>
		<attackPower>8</attackPower>
		<defensivePower>3</defensivePower>
		<bloodTotalVolume>30</bloodTotalVolume>
		<magicTotalVolume>30</magicTotalVolume>
		<attackLength>5</attackLength>
		<rank>2</rank>
		<srcInfo>
			<srcName>monster/baoxiangwang.png</srcName>
			<rowFramCount>4</rowFramCount>
			<colFramCount>9</colFramCount>
		</srcInfo>
		<leftFrames>
			<frame>
				<row>1</row>
				<col>0</col>
			</frame>
			<frame>
				<row>1</row>
				<col>1</col>
			</frame>
			<frame>
				<row>1</row>
				<col>2</col>
			</frame>
			<frame>
				<row>1</row>
				<col>3</col>
			</frame>
		</leftFrames>
		<rightFrames>
			<frame>
				<row>2</row>
				<col>0</col>
			</frame>
			<frame>
				<row>2</row>
				<col>1</col>
			</frame>
			<frame>
				<row>2</row>
				<col>2</col>
			</frame>
			<frame>
				<row>2</row>
				<col>3</col>
			</frame>
		</rightFrames>
	</monster>
	<monster>
		<monsterId>5</monsterId>
		<monsterName>蝙蝠</monsterName>
		<speed>10</speed>
		<attackPower>8</attackPower>
		<defensivePower>3</defensivePower>
		<bloodTotalVolume>30</bloodTotalVolume>
		<magicTotalVolume>30</magicTotalVolume>
		<attackLength>5</attackLength>
		<rank>2</rank>
		<srcInfo>
			<srcName>monster/bianfu.png</srcName>
			<rowFramCount>4</rowFramCount>
			<colFramCount>9</colFramCount>
		</srcInfo>
		<leftFrames>
			<frame>
				<row>1</row>
				<col>0</col>
			</frame>
			<frame>
				<row>1</row>
				<col>1</col>
			</frame>
			<frame>
				<row>1</row>
				<col>2</col>
			</frame>
			<frame>
				<row>1</row>
				<col>3</col>
			</frame>
		</leftFrames>
		<rightFrames>
			<frame>
				<row>2</row>
				<col>0</col>
			</frame>
			<frame>
				<row>2</row>
				<col>1</col>
			</frame>
			<frame>
				<row>2</row>
				<col>2</col>
			</frame>
			<frame>
				<row>2</row>
				<col>3</col>
			</frame>
		</rightFrames>
	</monster>
	<monster>
		<monsterId>6</monsterId>
		<monsterName>变种山羊</monsterName>
		<speed>10</speed>
		<attackPower>8</attackPower>
		<defensivePower>3</defensivePower>
		<bloodTotalVolume>30</bloodTotalVolume>
		<magicTotalVolume>30</magicTotalVolume>
		<attackLength>5</attackLength>
		<rank>2</rank>
		<srcInfo>
			<srcName>monster/bianzhongshanyang.png</srcName>
			<rowFramCount>4</rowFramCount>
			<colFramCount>9</colFramCount>
		</srcInfo>
		<leftFrames>
			<frame>
				<row>1</row>
				<col>0</col>
			</frame>
			<frame>
				<row>1</row>
				<col>1</col>
			</frame>
			<frame>
				<row>1</row>
				<col>2</col>
			</frame>
			<frame>
				<row>1</row>
				<col>3</col>
			</frame>
		</leftFrames>
		<rightFrames>
			<frame>
				<row>2</row>
				<col>0</col>
			</frame>
			<frame>
				<row>2</row>
				<col>1</col>
			</frame>
			<frame>
				<row>2</row>
				<col>2</col>
			</frame>
			<frame>
				<row>2</row>
				<col>3</col>
			</frame>
		</rightFrames>
	</monster>
	<monster>
		<monsterId>7</monsterId>
		<monsterName>变种幽灵</monsterName>
		<speed>10</speed>
		<attackPower>8</attackPower>
		<defensivePower>3</defensivePower>
		<bloodTotalVolume>30</bloodTotalVolume>
		<magicTotalVolume>30</magicTotalVolume>
		<attackLength>5</attackLength>
		<rank>2</rank>
		<srcInfo>
			<srcName>monster/bianzhongyouling.png</srcName>
			<rowFramCount>4</rowFramCount>
			<colFramCount>9</colFramCount>
		</srcInfo>
		<leftFrames>
			<frame>
				<row>1</row>
				<col>0</col>
			</frame>
			<frame>
				<row>1</row>
				<col>1</col>
			</frame>
			<frame>
				<row>1</row>
				<col>2</col>
			</frame>
			<frame>
				<row>1</row>
				<col>3</col>
			</frame>
		</leftFrames>
		<rightFrames>
			<frame>
				<row>2</row>
				<col>0</col>
			</frame>
			<frame>
				<row>2</row>
				<col>1</col>
			</frame>
			<frame>
				<row>2</row>
				<col>2</col>
			</frame>
			<frame>
				<row>2</row>
				<col>3</col>
			</frame>
		</rightFrames>
	</monster>
	<monster>
		<monsterId>8</monsterId>
		<monsterName>冰魔</monsterName>
		<speed>10</speed>
		<attackPower>8</attackPower>
		<defensivePower>3</defensivePower>
		<bloodTotalVolume>30</bloodTotalVolume>
		<magicTotalVolume>30</magicTotalVolume>
		<attackLength>5</attackLength>
		<rank>2</rank>
		<srcInfo>
			<srcName>monster/bingmo.png</srcName>
			<rowFramCount>4</rowFramCount>
			<colFramCount>9</colFramCount>
		</srcInfo>
		<leftFrames>
			<frame>
				<row>1</row>
				<col>0</col>
			</frame>
			<frame>
				<row>1</row>
				<col>1</col>
			</frame>
			<frame>
				<row>1</row>
				<col>2</col>
			</frame>
			<frame>
				<row>1</row>
				<col>3</col>
			</frame>
		</leftFrames>
		<rightFrames>
			<frame>
				<row>2</row>
				<col>0</col>
			</frame>
			<frame>
				<row>2</row>
				<col>1</col>
			</frame>
			<frame>
				<row>2</row>
				<col>2</col>
			</frame>
			<frame>
				<row>2</row>
				<col>3</col>
			</frame>
		</rightFrames>
	</monster>
	<monster>
		<monsterId>9</monsterId>
		<monsterName>村长</monsterName>
		<speed>10</speed>
		<attackPower>8</attackPower>
		<defensivePower>3</defensivePower>
		<bloodTotalVolume>30</bloodTotalVolume>
		<magicTotalVolume>30</magicTotalVolume>
		<attackLength>5</attackLength>
		<rank>2</rank>
		<srcInfo>
			<srcName>monster/cunzhang.png</srcName>
			<rowFramCount>4</rowFramCount>
			<colFramCount>9</colFramCount>
		</srcInfo>
		<leftFrames>
			<frame>
				<row>1</row>
				<col>0</col>
			</frame>
			<frame>
				<row>1</row>
				<col>1</col>
			</frame>
			<frame>
				<row>1</row>
				<col>2</col>
			</frame>
			<frame>
				<row>1</row>
				<col>3</col>
			</frame>
		</leftFrames>
		<rightFrames>
			<frame>
				<row>2</row>
				<col>0</col>
			</frame>
			<frame>
				<row>2</row>
				<col>1</col>
			</frame>
			<frame>
				<row>2</row>
				<col>2</col>
			</frame>
			<frame>
				<row>2</row>
				<col>3</col>
			</frame>
		</rightFrames>
	</monster>
	<monster>
		<monsterId>10</monsterId>
		<monsterName>掉渣欺负者</monsterName>
		<speed>10</speed>
		<attackPower>8</attackPower>
		<defensivePower>3</defensivePower>
		<bloodTotalVolume>30</bloodTotalVolume>
		<magicTotalVolume>30</magicTotalVolume>
		<attackLength>5</attackLength>
		<rank>2</rank>
		<srcInfo>
			<srcName>monster/diaozhaqifuzhe.png</srcName>
			<rowFramCount>4</rowFramCount>
			<colFramCount>9</colFramCount>
		</srcInfo>
		<leftFrames>
			<frame>
				<row>1</row>
				<col>0</col>
			</frame>
			<frame>
				<row>1</row>
				<col>1</col>
			</frame>
			<frame>
				<row>1</row>
				<col>2</col>
			</frame>
			<frame>
				<row>1</row>
				<col>3</col>
			</frame>
		</leftFrames>
		<rightFrames>
			<frame>
				<row>2</row>
				<col>0</col>
			</frame>
			<frame>
				<row>2</row>
				<col>1</col>
			</frame>
			<frame>
				<row>2</row>
				<col>2</col>
			</frame>
			<frame>
				<row>2</row>
				<col>3</col>
			</frame>
		</rightFrames>
	</monster>
	<monster>
		<monsterId>11</monsterId>
		<monsterName>哥布林</monsterName>
		<speed>10</speed>
		<attackPower>8</attackPower>
		<defensivePower>3</defensivePower>
		<bloodTotalVolume>30</bloodTotalVolume>
		<magicTotalVolume>30</magicTotalVolume>
		<attackLength>5</attackLength>
		<rank>2</rank>
		<srcInfo>
			<srcName>monster/gebulin.png</srcName>
			<rowFramCount>4</rowFramCount>
			<colFramCount>9</colFramCount>
		</srcInfo>
		<leftFrames>
			<frame>
				<row>1</row>
				<col>0</col>
			</frame>
			<frame>
				<row>1</row>
				<col>1</col>
			</frame>
			<frame>
				<row>1</row>
				<col>2</col>
			</frame>
			<frame>
				<row>1</row>
				<col>3</col>
			</frame>
		</leftFrames>
		<rightFrames>
			<frame>
				<row>2</row>
				<col>0</col>
			</frame>
			<frame>
				<row>2</row>
				<col>1</col>
			</frame>
			<frame>
				<row>2</row>
				<col>2</col>
			</frame>
			<frame>
				<row>2</row>
				<col>3</col>
			</frame>
		</rightFrames>
	</monster>
	<monster>
		<monsterId>12</monsterId>
		<monsterName>猴子</monsterName>
		<speed>10</speed>
		<attackPower>8</attackPower>
		<defensivePower>3</defensivePower>
		<bloodTotalVolume>30</bloodTotalVolume>
		<magicTotalVolume>30</magicTotalVolume>
		<attackLength>5</attackLength>
		<rank>2</rank>
		<srcInfo>
			<srcName>monster/houzi.png</srcName>
			<rowFramCount>4</rowFramCount>
			<colFramCount>9</colFramCount>
		</srcInfo>
		<leftFrames>
			<frame>
				<row>1</row>
				<col>0</col>
			</frame>
			<frame>
				<row>1</row>
				<col>1</col>
			</frame>
			<frame>
				<row>1</row>
				<col>2</col>
			</frame>
			<frame>
				<row>1</row>
				<col>3</col>
			</frame>
		</leftFrames>
		<rightFrames>
			<frame>
				<row>2</row>
				<col>0</col>
			</frame>
			<frame>
				<row>2</row>
				<col>1</col>
			</frame>
			<frame>
				<row>2</row>
				<col>2</col>
			</frame>
			<frame>
				<row>2</row>
				<col>3</col>
			</frame>
		</rightFrames>
	</monster>
	<monster>
		<monsterId>13</monsterId>
		<monsterName>火野猪</monsterName>
		<speed>10</speed>
		<attackPower>8</attackPower>
		<defensivePower>3</defensivePower>
		<bloodTotalVolume>30</bloodTotalVolume>
		<magicTotalVolume>30</magicTotalVolume>
		<attackLength>5</attackLength>
		<rank>2</rank>
		<srcInfo>
			<srcName>monster/huoyezhu.png</srcName>
			<rowFramCount>4</rowFramCount>
			<colFramCount>9</colFramCount>
		</srcInfo>
		<leftFrames>
			<frame>
				<row>1</row>
				<col>0</col>
			</frame>
			<frame>
				<row>1</row>
				<col>1</col>
			</frame>
			<frame>
				<row>1</row>
				<col>2</col>
			</frame>
			<frame>
				<row>1</row>
				<col>3</col>
			</frame>
		</leftFrames>
		<rightFrames>
			<frame>
				<row>2</row>
				<col>0</col>
			</frame>
			<frame>
				<row>2</row>
				<col>1</col>
			</frame>
			<frame>
				<row>2</row>
				<col>2</col>
			</frame>
			<frame>
				<row>2</row>
				<col>3</col>
			</frame>
		</rightFrames>
	</monster>
	<monster>
		<monsterId>14</monsterId>
		<monsterName>老虎王</monsterName>
		<speed>10</speed>
		<attackPower>8</attackPower>
		<defensivePower>3</defensivePower>
		<bloodTotalVolume>30</bloodTotalVolume>
		<magicTotalVolume>30</magicTotalVolume>
		<attackLength>5</attackLength>
		<rank>2</rank>
		<srcInfo>
			<srcName>monster/laohuwang.png</srcName>
			<rowFramCount>4</rowFramCount>
			<colFramCount>9</colFramCount>
		</srcInfo>
		<leftFrames>
			<frame>
				<row>1</row>
				<col>0</col>
			</frame>
			<frame>
				<row>1</row>
				<col>1</col>
			</frame>
			<frame>
				<row>1</row>
				<col>2</col>
			</frame>
			<frame>
				<row>1</row>
				<col>3</col>
			</frame>
		</leftFrames>
		<rightFrames>
			<frame>
				<row>2</row>
				<col>0</col>
			</frame>
			<frame>
				<row>2</row>
				<col>1</col>
			</frame>
			<frame>
				<row>2</row>
				<col>2</col>
			</frame>
			<frame>
				<row>2</row>
				<col>3</col>
			</frame>
		</rightFrames>
	</monster>
	<monster>
		<monsterId>15</monsterId>
		<monsterName>龙虾</monsterName>
		<speed>10</speed>
		<attackPower>8</attackPower>
		<defensivePower>3</defensivePower>
		<bloodTotalVolume>30</bloodTotalVolume>
		<magicTotalVolume>30</magicTotalVolume>
		<attackLength>5</attackLength>
		<rank>2</rank>
		<srcInfo>
			<srcName>monster/longxia.png</srcName>
			<rowFramCount>4</rowFramCount>
			<colFramCount>9</colFramCount>
		</srcInfo>
		<leftFrames>
			<frame>
				<row>1</row>
				<col>0</col>
			</frame>
			<frame>
				<row>1</row>
				<col>1</col>
			</frame>
			<frame>
				<row>1</row>
				<col>2</col>
			</frame>
			<frame>
				<row>1</row>
				<col>3</col>
			</frame>
		</leftFrames>
		<rightFrames>
			<frame>
				<row>2</row>
				<col>0</col>
			</frame>
			<frame>
				<row>2</row>
				<col>1</col>
			</frame>
			<frame>
				<row>2</row>
				<col>2</col>
			</frame>
			<frame>
				<row>2</row>
				<col>3</col>
			</frame>
		</rightFrames>
	</monster>
	<monster>
		<monsterId>16</monsterId>
		<monsterName>龙虾王</monsterName>
		<speed>10</speed>
		<attackPower>8</attackPower>
		<defensivePower>3</defensivePower>
		<bloodTotalVolume>30</bloodTotalVolume>
		<magicTotalVolume>30</magicTotalVolume>
		<attackLength>5</attackLength>
		<rank>2</rank>
		<srcInfo>
			<srcName>monster/longxiawang.png</srcName>
			<rowFramCount>4</rowFramCount>
			<colFramCount>9</colFramCount>
		</srcInfo>
		<leftFrames>
			<frame>
				<row>1</row>
				<col>0</col>
			</frame>
			<frame>
				<row>1</row>
				<col>1</col>
			</frame>
			<frame>
				<row>1</row>
				<col>2</col>
			</frame>
			<frame>
				<row>1</row>
				<col>3</col>
			</frame>
		</leftFrames>
		<rightFrames>
			<frame>
				<row>2</row>
				<col>0</col>
			</frame>
			<frame>
				<row>2</row>
				<col>1</col>
			</frame>
			<frame>
				<row>2</row>
				<col>2</col>
			</frame>
			<frame>
				<row>2</row>
				<col>3</col>
			</frame>
		</rightFrames>
	</monster>
	<monster>
		<monsterId>17</monsterId>
		<monsterName>螃蟹</monsterName>
		<speed>10</speed>
		<attackPower>8</attackPower>
		<defensivePower>3</defensivePower>
		<bloodTotalVolume>30</bloodTotalVolume>
		<magicTotalVolume>30</magicTotalVolume>
		<attackLength>5</attackLength>
		<rank>2</rank>
		<srcInfo>
			<srcName>monster/pangxie.png</srcName>
			<rowFramCount>4</rowFramCount>
			<colFramCount>9</colFramCount>
		</srcInfo>
		<leftFrames>
			<frame>
				<row>1</row>
				<col>0</col>
			</frame>
			<frame>
				<row>1</row>
				<col>1</col>
			</frame>
			<frame>
				<row>1</row>
				<col>2</col>
			</frame>
			<frame>
				<row>1</row>
				<col>3</col>
			</frame>
		</leftFrames>
		<rightFrames>
			<frame>
				<row>2</row>
				<col>0</col>
			</frame>
			<frame>
				<row>2</row>
				<col>1</col>
			</frame>
			<frame>
				<row>2</row>
				<col>2</col>
			</frame>
			<frame>
				<row>2</row>
				<col>3</col>
			</frame>
		</rightFrames>
	</monster>
	<monster>
		<monsterId>18</monsterId>
		<monsterName>老虎</monsterName>
		<speed>10</speed>
		<attackPower>8</attackPower>
		<defensivePower>3</defensivePower>
		<bloodTotalVolume>30</bloodTotalVolume>
		<magicTotalVolume>30</magicTotalVolume>
		<attackLength>5</attackLength>
		<rank>2</rank>
		<srcInfo>
			<srcName>monster/laohu.png</srcName>
			<rowFramCount>4</rowFramCount>
			<colFramCount>9</colFramCount>
		</srcInfo>
		<leftFrames>
			<frame>
				<row>1</row>
				<col>0</col>
			</frame>
			<frame>
				<row>1</row>
				<col>1</col>
			</frame>
			<frame>
				<row>1</row>
				<col>2</col>
			</frame>
			<frame>
				<row>1</row>
				<col>3</col>
			</frame>
		</leftFrames>
		<rightFrames>
			<frame>
				<row>2</row>
				<col>0</col>
			</frame>
			<frame>
				<row>2</row>
				<col>1</col>
			</frame>
			<frame>
				<row>2</row>
				<col>2</col>
			</frame>
			<frame>
				<row>2</row>
				<col>3</col>
			</frame>
		</rightFrames>
	</monster>
	<monster>
		<monsterId>19</monsterId>
		<monsterName>酋长土道</monsterName>
		<speed>10</speed>
		<attackPower>8</attackPower>
		<defensivePower>3</defensivePower>
		<bloodTotalVolume>30</bloodTotalVolume>
		<magicTotalVolume>30</magicTotalVolume>
		<attackLength>5</attackLength>
		<rank>2</rank>
		<srcInfo>
			<srcName>monster/qiuzhangtudao.png</srcName>
			<rowFramCount>4</rowFramCount>
			<colFramCount>9</colFramCount>
		</srcInfo>
		<leftFrames>
			<frame>
				<row>1</row>
				<col>0</col>
			</frame>
			<frame>
				<row>1</row>
				<col>1</col>
			</frame>
			<frame>
				<row>1</row>
				<col>2</col>
			</frame>
			<frame>
				<row>1</row>
				<col>3</col>
			</frame>
		</leftFrames>
		<rightFrames>
			<frame>
				<row>2</row>
				<col>0</col>
			</frame>
			<frame>
				<row>2</row>
				<col>1</col>
			</frame>
			<frame>
				<row>2</row>
				<col>2</col>
			</frame>
			<frame>
				<row>2</row>
				<col>3</col>
			</frame>
		</rightFrames>
	</monster>
	<monster>
		<monsterId>20</monsterId>
		<monsterName>小老虎</monsterName>
		<speed>10</speed>
		<attackPower>8</attackPower>
		<defensivePower>3</defensivePower>
		<bloodTotalVolume>30</bloodTotalVolume>
		<magicTotalVolume>30</magicTotalVolume>
		<attackLength>5</attackLength>
		<rank>2</rank>
		<srcInfo>
			<srcName>monster/xiaolaohu.png</srcName>
			<rowFramCount>4</rowFramCount>
			<colFramCount>9</colFramCount>
		</srcInfo>
		<leftFrames>
			<frame>
				<row>1</row>
				<col>0</col>
			</frame>
			<frame>
				<row>1</row>
				<col>1</col>
			</frame>
			<frame>
				<row>1</row>
				<col>2</col>
			</frame>
			<frame>
				<row>1</row>
				<col>3</col>
			</frame>
		</leftFrames>
		<rightFrames>
			<frame>
				<row>2</row>
				<col>0</col>
			</frame>
			<frame>
				<row>2</row>
				<col>1</col>
			</frame>
			<frame>
				<row>2</row>
				<col>2</col>
			</frame>
			<frame>
				<row>2</row>
				<col>3</col>
			</frame>
		</rightFrames>
	</monster>
	<monster>
		<monsterId>21</monsterId>
		<monsterName>学生</monsterName>
		<speed>10</speed>
		<attackPower>8</attackPower>
		<defensivePower>3</defensivePower>
		<bloodTotalVolume>30</bloodTotalVolume>
		<magicTotalVolume>30</magicTotalVolume>
		<attackLength>5</attackLength>
		<rank>2</rank>
		<srcInfo>
			<srcName>monster/xuesheng.png</srcName>
			<rowFramCount>4</rowFramCount>
			<colFramCount>9</colFramCount>
		</srcInfo>
		<leftFrames>
			<frame>
				<row>1</row>
				<col>0</col>
			</frame>
			<frame>
				<row>1</row>
				<col>1</col>
			</frame>
			<frame>
				<row>1</row>
				<col>2</col>
			</frame>
			<frame>
				<row>1</row>
				<col>3</col>
			</frame>
		</leftFrames>
		<rightFrames>
			<frame>
				<row>2</row>
				<col>0</col>
			</frame>
			<frame>
				<row>2</row>
				<col>1</col>
			</frame>
			<frame>
				<row>2</row>
				<col>2</col>
			</frame>
			<frame>
				<row>2</row>
				<col>3</col>
			</frame>
		</rightFrames>
	</monster>
	<monster>
		<monsterId>22</monsterId>
		<monsterName>炎魔</monsterName>
		<speed>10</speed>
		<attackPower>8</attackPower>
		<defensivePower>3</defensivePower>
		<bloodTotalVolume>30</bloodTotalVolume>
		<magicTotalVolume>30</magicTotalVolume>
		<attackLength>5</attackLength>
		<rank>2</rank>
		<srcInfo>
			<srcName>monster/yanmo.png</srcName>
			<rowFramCount>4</rowFramCount>
			<colFramCount>9</colFramCount>
		</srcInfo>
		<leftFrames>
			<frame>
				<row>1</row>
				<col>0</col>
			</frame>
			<frame>
				<row>1</row>
				<col>1</col>
			</frame>
			<frame>
				<row>1</row>
				<col>2</col>
			</frame>
			<frame>
				<row>1</row>
				<col>3</col>
			</frame>
		</leftFrames>
		<rightFrames>
			<frame>
				<row>2</row>
				<col>0</col>
			</frame>
			<frame>
				<row>2</row>
				<col>1</col>
			</frame>
			<frame>
				<row>2</row>
				<col>2</col>
			</frame>
			<frame>
				<row>2</row>
				<col>3</col>
			</frame>
		</rightFrames>
	</monster>
</root>